GoogleImages_Download/GoogleImagesDownload.py
GoogleImages_Download-1.0.6.dist-info/LICENSE.txt
GoogleImages_Download-1.0.6.dist-info/METADATA
GoogleImages_Download-1.0.6.dist-info/WHEEL
GoogleImages_Download-1.0.6.dist-info/entry_points.txt
GoogleImages_Download-1.0.6.dist-info/top_level.txt
GoogleImages_Download-1.0.6.dist-info/RECORD
