Metadata-Version: 2.1
Name: GoogleImages-Download
Version: 1.0.6
Summary: A Python Script for downloading bulk of images from google.
Home-page: https://github.com/khannoaman/GoogleImages-Download
Author: MOHAMMAD NOAMAN KHAN
Author-email: khan.noamaan@gmail.com
License: MIT
Platform: UNKNOWN
Classifier: License :: OSI Approved :: MIT License
Classifier: Programming Language :: Python :: 3
Classifier: Programming Language :: Python :: 3.7
Requires-Dist: requests
Requires-Dist: selenium
Requires-Dist: tqdm
Requires-Dist: chromedriver-binary
Requires-Dist: chromedriver-binary (==83.0.4103.39.0)
